Workbook
Name aporte: Planilha1!$D$18
Name patrimonio: Planilha1!$D$21
Name qtd_anos: Planilha1!$D$19
Name rendimento_carteira: Planilha1!$D$14
Name salario: Planilha1!$D$13
Name sugestao_investimento: Planilha1!$D$15
Name taxa_mensal: Planilha1!$D$20

Sheet Planilha1
B12: CONFIRGURAÇÕES
B13: Salário | D13: 2000
B14: Rendimento Carteira | D14: 0.0079
B15: Sugestão de Investimento (30%) | D15: =D13*0.3 -> 600
B17: INVESTIMENTO MENSAL
B18: Quanto investir por mês? | D18: 500
B19: Por Quantos Anos? | D19: 5
B20: Taxa de Rendimento Mensal? | D20: 0.0079
B21: Patrimônio acumulado? | D21: =FV(taxa_mensal,qtd_anos*12,-aporte) -> 38191.003
B22: Dividendos Mensais? | D22: =patrimonio*rendimento_carteira -> 301.70892
B24: Cenários | D24: Dividendo
A25: 2 | B25: Quanto em 2 Anos? | C25: =FV($D$20,$A25*12,-$D$18) -> 13156.063 | D25: =C25*rendimento_carteira -> 103.9329
A26: 5 | B26: Quanto em 5 Anos? | C26: =FV($D$20,$A26*12,-$D$18) -> 38191.003 | D26: =C26*rendimento_carteira -> 301.70892
A27: 10 | B27: Quanto em 10 Anos? | C27: =FV($D$20,$A27*12,-$D$18) -> 99427.138 | D27: =C27*rendimento_carteira -> 785.47439
A28: 20 | B28: Quanto em 20 Anos? | C28: =FV($D$20,$A28*12,-$D$18) -> 355049.22 | D28: =C28*rendimento_carteira -> 2804.8888
A29: 30 | B29: Quanto em 30 Anos? | C29: =FV($D$20,$A29*12,-$D$18) -> 1012240.5 | D29: =C29*rendimento_carteira -> 7996.6999
B46: Perfil | C46: Moderado
B47: VALOR A SER INVESTIDO POR MÊS | C47: =aporte -> 500
B49: TIPO DE FII | C49: Percentual Sugerido | D49: Valores
B50: PAPEL | C50: =VLOOKUP($C$46&"-"&$B50,Planilha3!$B$3:$E$20,4,0) -> 0.32 | D50: =C50*$C$47 -> 160
B51: TIJOLO | C51: =VLOOKUP($C$46&"-"&$B51,Planilha3!$B$3:$E$20,4,0) -> 0.35 | D51: =C51*$C$47 -> 175
B52: HÍBRIDOS | C52: =VLOOKUP($C$46&"-"&$B52,Planilha3!$B$3:$E$20,4,0) -> 0.08 | D52: =C52*$C$47 -> 40
B53: FOFs | C53: =VLOOKUP($C$46&"-"&$B53,Planilha3!$B$3:$E$20,4,0) -> 0.05 | D53: =C53*$C$47 -> 25
B54: DESENVOLVIMENTO | C54: =VLOOKUP($C$46&"-"&$B54,Planilha3!$B$3:$E$20,4,0) -> 0.1 | D54: =C54*$C$47 -> 50
B55: HOTELARIAS | C55: =VLOOKUP($C$46&"-"&$B55,Planilha3!$B$3:$E$20,4,0) -> 0.1 | D55: =C55*$C$47 -> 50
D56: =SUM(D50:D55) -> 500

Sheet Planilha3
B2: CHAVE | C2: PERFIL | D2: TIPO DE FII | E2: %
B3: =C3&"-"&D3 -> Conservador-PAPEL | C3: Conservador | D3: PAPEL | E3: 0.3 | H3: Moderado-TIJOLO
B4: =C4&"-"&D4 -> Conservador-TIJOLO | C4: Conservador | D4: TIJOLO | E4: 0.5 | G4: % | H4: =VLOOKUP(H3,$B$3:$E$20,4,0) -> 0.35
B5: =C5&"-"&D5 -> Conservador-HÍBRIDOS | C5: Conservador | D5: HÍBRIDOS | E5: 0.1
B6: =C6&"-"&D6 -> Conservador-FOFs | C6: Conservador | D6: FOFs | E6: 0.1
B7: =C7&"-"&D7 -> Conservador-DESENVOLVIMENTO | C7: Conservador | D7: DESENVOLVIMENTO | E7: 0
B8: =C8&"-"&D8 -> Conservador-HOTELARIAS | C8: Conservador | D8: HOTELARIAS | E8: 0
B9: =C9&"-"&D9 -> Moderado-PAPEL | C9: Moderado | D9: PAPEL | E9: 0.32
B10: =C10&"-"&D10 -> Moderado-TIJOLO | C10: Moderado | D10: TIJOLO | E10: 0.35
B11: =C11&"-"&D11 -> Moderado-HÍBRIDOS | C11: Moderado | D11: HÍBRIDOS | E11: 0.08
B12: =C12&"-"&D12 -> Moderado-FOFs | C12: Moderado | D12: FOFs | E12: 0.05
B13: =C13&"-"&D13 -> Moderado-DESENVOLVIMENTO | C13: Moderado | D13: DESENVOLVIMENTO | E13: 0.1
B14: =C14&"-"&D14 -> Moderado-HOTELARIAS | C14: Moderado | D14: HOTELARIAS | E14: 0.1
B15: =C15&"-"&D15 -> Agressivo-PAPEL | C15: Agressivo | D15: PAPEL | E15: 0.5
B16: =C16&"-"&D16 -> Agressivo-TIJOLO | C16: Agressivo | D16: TIJOLO | E16: 0.1
... B20: =C20&"-"&D20 -> Agressivo-HOTELARIAS | C20: Agressivo | D20: HOTELARIAS | E20: 0.1
C1048576: Conservador

Sheet Planilha2
D5: Tipo de FII | E5: Descrição | F5: Exemplos de Ativos
D6: FII de Tijolo | E6: Investem diretamente em imóveis físicos com o objetivo de geração de renda com aluguel. | F6: Shoppings, galpões logísticos, escritórios, hospitais
D7: FII de Papel | E7: Investem em títulos e valores mobiliários ligados ao setor imobiliário | F7: CRIs (Certificados de Recebíveis Imobiliários), LCIs, cotas de outso FIIs
D8: FII Híbrido | E8: Combina ativos de tijolo e de papel, buscando diversificação e maior flexibilidade. | F8: Combinação de imóveis e CRIs, por exemplo
D9: FII de Desenvolvimento | E9: Focados na construção ou incorporação de imóveis para posterior venda ou locação. | F9: Loteamentos, prédios residenciais/comerciais em construção
D10: FII de Fundos (FOF) | E10: Investe em cotas de outros FIIs, funcionando como um fundo de fundos. | F10: Carteiras diversificadas de FIIs
D11: FII de Agências Bancárias | E11: Investe em imóveis alugados para instituições financeiras. | F11: Agências do Banco do Brasil, Caixa, etc.
D12: FII de Hospitalidade | E12: Focado em imóveis do setor hoteleiro e de turismo. | F12: Hotéis, resorts
D13: FII Logístico/Industrial | E13: Especializados em imóveis voltados a armazenamento, distruibuição e produção. | F13: Centros de distruibuição, galpões industriais
